pypalette/__init__.py
pypalette/go-palette-linux.so
pypalette/go-palette-mac.so
pypalette-0.1.6.dist-info/LICENSE
pypalette-0.1.6.dist-info/METADATA
pypalette-0.1.6.dist-info/WHEEL
pypalette-0.1.6.dist-info/top_level.txt
pypalette-0.1.6.dist-info/RECORD
