Metadata-Version: 2.1
Name: pypalette
Version: 0.1.6
Summary: Extract prominent colors from images! Python wrapper for `https://github.com/dayvonjersen/vibrant`.
Home-page: https://github.com/BiLiangDevelop/py-go-palette
Author: BiLiangDevelop && frkhit
Author-email: frkhit@gmail.com
License: MIT
Platform: UNKNOWN
Classifier: Development Status :: 4 - Beta
Classifier: Intended Audience :: Developers
Classifier: Intended Audience :: Other Audience
Classifier: Intended Audience :: Science/Research
Classifier: License :: OSI Approved :: MIT License
Classifier: Natural Language :: English
Classifier: Programming Language :: Python
Classifier: Programming Language :: Python :: 3.5
Classifier: Programming Language :: Python :: 3.6
Classifier: Programming Language :: Python :: 3.7
Classifier: Topic :: Scientific/Engineering
Classifier: Topic :: Software Development :: Libraries
Classifier: Topic :: Utilities
Requires-Dist: Pillow
Requires-Dist: requests
